newbookapi/__init__.py
newbookapi/newbookapi.py
newbookapi-0.1.0.dist-info/METADATA
newbookapi-0.1.0.dist-info/WHEEL
newbookapi-0.1.0.dist-info/top_level.txt
newbookapi-0.1.0.dist-info/RECORD
