Metadata-Version: 2.1
Name: newbookapi
Version: 0.1.0
Summary: A Python client for the Newbook API.
Home-page: https://www.travelresorts.com/
Author: Manzar nouman
Author-email: manzarnouman@gmail.com
Project-URL: Source, https://github.com/TridentMarketing/newbook-api/tree/packagify
Classifier: Programming Language :: Python :: 3
Classifier: License :: OSI Approved :: MIT License
Classifier: Operating System :: OS Independent
Requires-Python: >=3.6
Requires-Dist: requests
